Deneme/Deneme.py
Deneme/__init__.py
Ayalni2289-0.0.1.dist-info/LICENSE
Ayalni2289-0.0.1.dist-info/METADATA
Ayalni2289-0.0.1.dist-info/WHEEL
Ayalni2289-0.0.1.dist-info/top_level.txt
Ayalni2289-0.0.1.dist-info/RECORD
