Metadata-Version: 2.1
Name: Ayalni2289
Version: 0.0.1
Summary: Just a Hello World Command
Home-page: https://github.com/Ayalni2289/Eksbt_Python_Paket
Author: Ali Yalnız
Author-email: Ali Yalnız <aliyalniz2289@gmail.com>
Project-URL: Homepage, https://github.com/Ayalni2289/Eksbt_Python_Paket
Classifier: Programming Language :: Python :: 3
Classifier: License :: OSI Approved :: MIT License
Classifier: Operating System :: OS Independent
Requires-Python: >=3.5.5
License-File: LICENSE
